README.md
setup.py
piedpiper/__init__.py
piedpiper/main.py
piedpiper/version.py
piedpiper.egg-info/PKG-INFO
piedpiper.egg-info/SOURCES.txt
piedpiper.egg-info/dependency_links.txt
piedpiper.egg-info/top_level.txt