Metadata-Version: 1.1
Name: piedpiper
Version: 0.0.2
Summary: Debug context manager for chained commands.
Home-page: http://github.com/endrebak/piedpiper
Author: Endre Bakken Stovner
Author-email: endrebak85@gmail.com
License: MIT
Keywords: Debugging
Platform: UNKNOWN
Classifier: Programming Language :: Python :: 2.7
Classifier: Programming Language :: Python :: 3
Classifier: Development Status :: 4 - Beta
Classifier: Environment :: Other Environment
Classifier: Intended Audience :: Developers
Classifier: Intended Audience :: Science/Research
Classifier: License :: OSI Approved :: MIT License
Classifier: Operating System :: POSIX :: Linux
Classifier: Operating System :: MacOS :: MacOS X
Classifier: Topic :: Scientific/Engineering
